flask_cachecontrol/__init__.py
flask_cachecontrol/after_this_request.py
flask_cachecontrol/cache.py
flask_cachecontrol/callback.py
flask_cachecontrol/decorate.py
flask_cachecontrol/error.py
flask_cachecontrol/evaluator.py
Flask_CacheControl-0.3.0.dist-info/LICENSE
Flask_CacheControl-0.3.0.dist-info/METADATA
Flask_CacheControl-0.3.0.dist-info/WHEEL
Flask_CacheControl-0.3.0.dist-info/top_level.txt
Flask_CacheControl-0.3.0.dist-info/RECORD
