Metadata-Version: 2.1
Name: Flask-CacheControl
Version: 0.3.0
Summary: Set Cache-Control headers on the Flask response
Home-page: https://github.com/twiebe/Flask-CacheControl
Author: Thomas Wiebe
Author-email: thomas+code@heimblick.net
License: BSD
Platform: any
Classifier: Environment :: Web Environment
Classifier: Intended Audience :: Developers
Classifier: License :: OSI Approved :: BSD License
Classifier: Operating System :: OS Independent
Classifier: Programming Language :: Python
Classifier: Topic :: Internet :: WWW/HTTP :: Dynamic Content
Classifier: Topic :: Software Development :: Libraries :: Python Modules
Requires-Python: >=3.3
Provides-Extra: test
License-File: LICENSE
